{
  "project_id": "speedball",
  "session_id": "sess_511c75912d234cb6872e5cbfee5ce25f",
  "label": "chat_plan",
  "logged_at": "2026-02-01T19:59:52.682731Z",
  "task_plan": {
    "plan_id": "plan_cf8937d96d30",
    "created_at": "2026-02-01T19:59:52.678406Z",
    "source_state_id": "sess_511c75912d234cb6872e5cbfee5ce25f",
    "tasks": [
      {
        "id": "task_chat_1a",
        "agent": "chat_1a",
        "input_ref": "chat_memory",
        "output_ref": "chat_1a_output",
        "depends_on": []
      },
      {
        "id": "task_chat_1b",
        "agent": "chat_1b",
        "input_ref": "chat_1a_output",
        "output_ref": "chat_1b_output",
        "depends_on": [
          "task_chat_1a"
        ]
      },
      {
        "id": "task_chat_1c",
        "agent": "chat_1c",
        "input_ref": "chat_1b_output",
        "output_ref": "chat_1c_output",
        "depends_on": [
          "task_chat_1b"
        ]
      }
    ]
  },
  "task_context": {
    "task_chat_1a": {
      "message": "je veux 90 secondes et une musique hip hop avec du classique dedans et une ambiance dramatique",
      "project_empty": true,
      "empty_strata": {
        "n0": true,
        "n1": true,
        "n2": true,
        "n3": true,
        "n4": true,
        "n5": true
      },
      "pending_questions": [],
      "pending_rounds": 0,
      "chat_mode": "clarify"
    },
    "task_chat_1b": {},
    "task_chat_1c": {}
  },
  "next_action": "edit_mode"
}